LICENSE
README.rst
setup.py
aide_core.egg-info/PKG-INFO
aide_core.egg-info/SOURCES.txt
aide_core.egg-info/dependency_links.txt
aide_core.egg-info/entry_points.txt
aide_core.egg-info/requires.txt
aide_core.egg-info/top_level.txt
platformio/__init__.py
platformio/__main__.py
platformio/app.py
platformio/cache.py
platformio/cli.py
platformio/compat.py
platformio/exception.py
platformio/fs.py
platformio/http.py
platformio/maintenance.py
platformio/proc.py
platformio/public.py
platformio/telemetry.py
platformio/util.py
platformio/account/__init__.py
platformio/account/cli.py
platformio/account/client.py
platformio/account/validate.py
platformio/account/commands/__init__.py
platformio/account/commands/destroy.py
platformio/account/commands/forgot.py
platformio/account/commands/login.py
platformio/account/commands/logout.py
platformio/account/commands/password.py
platformio/account/commands/register.py
platformio/account/commands/show.py
platformio/account/commands/token.py
platformio/account/commands/update.py
platformio/account/org/__init__.py
platformio/account/org/cli.py
platformio/account/org/commands/__init__.py
platformio/account/org/commands/add.py
platformio/account/org/commands/create.py
platformio/account/org/commands/destroy.py
platformio/account/org/commands/list.py
platformio/account/org/commands/remove.py
platformio/account/org/commands/update.py
platformio/account/team/__init__.py
platformio/account/team/cli.py
platformio/account/team/commands/__init__.py
platformio/account/team/commands/add.py
platformio/account/team/commands/create.py
platformio/account/team/commands/destroy.py
platformio/account/team/commands/list.py
platformio/account/team/commands/remove.py
platformio/account/team/commands/update.py
platformio/assets/system/99-platformio-udev.rules
platformio/builder/__init__.py
platformio/builder/main.py
platformio/builder/tools/__init__.py
platformio/builder/tools/pioasm.py
platformio/builder/tools/piobuild.py
platformio/builder/tools/piohooks.py
platformio/builder/tools/pioino.py
platformio/builder/tools/piointegration.py
platformio/builder/tools/piolib.py
platformio/builder/tools/piomaxlen.py
platformio/builder/tools/piomisc.py
