Metadata-Version: 2.1
Name: aide-core
Version: 1.0.1000
Summary: A professional collaborative platform for embedded development. Cross-platform IDE and Unified Debugger. Static Code Analyzer and Remote Unit Testing. Multi-platform and Multi-architecture Build System. Firmware File Explorer and Memory Inspection. IoT, Arduino, CMSIS, ESP-IDF, FreeRTOS, libOpenCM3, mbedOS, Pulp OS, SPL, STM32Cube, Zephyr RTOS, ARM, AVR, Espressif (ESP8266/ESP32), FPGA, MCS-51 (8051), MSP430, Nordic (nRF51/nRF52), NXP i.MX RT, PIC32, RISC-V, STMicroelectronics (STM8/STM
Home-page: https://platformio.org
Author: PlatformIO Labs
Author-email: contact@piolabs.com
License: Apache Software License
Keywords: iot,embedded,arduino,mbed,esp8266,esp32,fpga,firmware,continuous-integration,cloud-ide,avr,arm,ide,unit-testing,hardware,verilog,microcontroller,debug
Classifier: Development Status :: 5 - Production/Stable
Classifier: Environment :: Console
Classifier: Intended Audience :: Developers
Classifier: License :: OSI Approved :: Apache Software License
Classifier: Operating System :: OS Independent
Classifier: Programming Language :: C
Classifier: Programming Language :: Python
Classifier: Programming Language :: Python :: 3
Classifier: Topic :: Software Development
Classifier: Topic :: Software Development :: Build Tools
Classifier: Topic :: Software Development :: Compilers
Requires-Python: >=3.6
License-File: LICENSE
